AUTHORS
LICENSE
MANIFEST.in
README.md
__init__.py
requirements.txt
setup.py
inkblock/__init__.py
inkblock/main.py
inkblock.egg-info/PKG-INFO
inkblock.egg-info/SOURCES.txt
inkblock.egg-info/dependency_links.txt
inkblock.egg-info/entry_points.txt
inkblock.egg-info/pbr.json
inkblock.egg-info/requires.txt
inkblock.egg-info/top_level.txt
inkblock/templates/sitemap.xml
inkblock/templates/social.html