Metadata-Version: 1.1
Name: inkblock
Version: 0.6.2
Summary: A simple, end-to-end publishing platform.
Home-page: https://github.com/skoczen/inkblock
Author: Steven Skoczen
Author-email: skoczen@gmail.com
License: UNKNOWN
Download-URL: ['https://github.com/skoczen/inkblock/tarball/0.6.2']
Keywords: static,generator,social
Platform: UNKNOWN
Classifier: Programming Language :: Python
Classifier: Intended Audience :: Developers
Classifier: License :: OSI Approved :: MIT License
Classifier: Operating System :: OS Independent
Classifier: Development Status :: 4 - Beta
Classifier: Environment :: Web Environment
Classifier: Intended Audience :: Developers
Classifier: Topic :: Software Development :: Libraries :: Python Modules
